tejasayya/__init__.py
tejasayya/__main__.py
tejasayya-1.0.3.dist-info/METADATA
tejasayya-1.0.3.dist-info/WHEEL
tejasayya-1.0.3.dist-info/entry_points.txt
tejasayya-1.0.3.dist-info/top_level.txt
tejasayya-1.0.3.dist-info/RECORD
