Metadata-Version: 2.4
Name: tejasayya
Version: 1.0.3
Summary: CLI package that introduces Teja Swaroop Sayya 🚀
Author: Teja Swaroop Sayya
Author-email: tejasayya@gmail.com
License: MIT
Requires-Python: >=3.7
Dynamic: author
Dynamic: author-email
Dynamic: license
Dynamic: requires-python
Dynamic: summary
